DaiNiWanzhuanVisualStudio/README.md
DaiNiWanzhuanVisualStudio/__init__.py
DaiNiWanzhuanVisualStudio/__main__.py
DaiNiWanzhuanVisualStudio/file.epub
DaiNiWanzhuanVisualStudio/index.html
DaiNiWanzhuanVisualStudio/css/__init__.py
DaiNiWanzhuanVisualStudio/css/annotations.css
DaiNiWanzhuanVisualStudio/css/main.css
DaiNiWanzhuanVisualStudio/css/normalize.css
DaiNiWanzhuanVisualStudio/css/popup.css
DaiNiWanzhuanVisualStudio/font/__init__.py
DaiNiWanzhuanVisualStudio/font/fontello.eot
DaiNiWanzhuanVisualStudio/font/fontello.svg
DaiNiWanzhuanVisualStudio/font/fontello.ttf
DaiNiWanzhuanVisualStudio/font/fontello.woff
DaiNiWanzhuanVisualStudio/img/__init__.py
DaiNiWanzhuanVisualStudio/img/annotator-glyph-sprite.png
DaiNiWanzhuanVisualStudio/img/annotator-icon-sprite.png
DaiNiWanzhuanVisualStudio/img/apple-touch-icon.png
DaiNiWanzhuanVisualStudio/img/cancelfullscreen.png
DaiNiWanzhuanVisualStudio/img/close.png
DaiNiWanzhuanVisualStudio/img/fullscreen.png
DaiNiWanzhuanVisualStudio/img/loader.gif
DaiNiWanzhuanVisualStudio/img/menu-icon.png
DaiNiWanzhuanVisualStudio/img/save.png
DaiNiWanzhuanVisualStudio/img/saved.png
DaiNiWanzhuanVisualStudio/img/settings-s.png
DaiNiWanzhuanVisualStudio/img/settings.png
DaiNiWanzhuanVisualStudio/img/star.png
DaiNiWanzhuanVisualStudio/js/__init__.py
DaiNiWanzhuanVisualStudio/js/epub.js
DaiNiWanzhuanVisualStudio/js/epub.min.js
DaiNiWanzhuanVisualStudio/js/epub.min.map
DaiNiWanzhuanVisualStudio/js/hooks.min.js
DaiNiWanzhuanVisualStudio/js/hooks.min.map
DaiNiWanzhuanVisualStudio/js/reader.js
DaiNiWanzhuanVisualStudio/js/reader.js.map
DaiNiWanzhuanVisualStudio/js/reader.min.js
DaiNiWanzhuanVisualStudio/js/reader.min.map
DaiNiWanzhuanVisualStudio/js/hooks/__init__.py
DaiNiWanzhuanVisualStudio/js/hooks/extensions/__init__.py
DaiNiWanzhuanVisualStudio/js/hooks/extensions/highlight.js
DaiNiWanzhuanVisualStudio/js/libs/__init__.py
DaiNiWanzhuanVisualStudio/js/libs/jquery.min.js
DaiNiWanzhuanVisualStudio/js/libs/localforage.min.js
dai_ni_wanzhuan_visual_studio-2024.3.4.0.dist-info/METADATA
dai_ni_wanzhuan_visual_studio-2024.3.4.0.dist-info/WHEEL
dai_ni_wanzhuan_visual_studio-2024.3.4.0.dist-info/entry_points.txt
dai_ni_wanzhuan_visual_studio-2024.3.4.0.dist-info/top_level.txt
dai_ni_wanzhuan_visual_studio-2024.3.4.0.dist-info/RECORD
